{
  "as_of": "2026-03-05T19:10:07.085345+00:00",
  "strategy": "grid_dca_hybrid",
  "current_regime": "cash",
  "adx_value": 33.392015,
  "grid_levels": {},
  "prices": {
    "WBTCDAI": 71237.2,
    "WETHDAI": 2079.75,
    "WSOLDAI": 89.11,
    "FRAXDAI": 0.5816
  },
  "positions": [],
  "trades": [],
  "equity": [
    {
      "ts": 1772737290,
      "equity": 20000.0,
      "cash": 20000.0
    },
    {
      "ts": 1772737497,
      "equity": 20000.0,
      "cash": 20000.0
    },
    {
      "ts": 1772737806,
      "equity": 20000.0,
      "cash": 20000.0
    }
  ],
  "metrics": [
    {
      "ts": 1772737807,
      "duration_ms": 12535,
      "status": "ok",
      "buys": 0,
      "sells": 0,
      "trades": 0,
      "fees": 0.0,
      "positions": 0,
      "equity": 20000.0,
      "cash": 20000.0,
      "note": ""
    },
    {
      "ts": 1772737498,
      "duration_ms": 6864,
      "status": "ok",
      "buys": 0,
      "sells": 0,
      "trades": 0,
      "fees": 0.0,
      "positions": 0,
      "equity": 20000.0,
      "cash": 20000.0,
      "note": ""
    },
    {
      "ts": 1772737290,
      "duration_ms": 6510,
      "status": "ok",
      "buys": 0,
      "sells": 0,
      "trades": 0,
      "fees": 0.0,
      "positions": 0,
      "equity": 20000.0,
      "cash": 20000.0,
      "note": ""
    }
  ]
}